terminal_utils/__init__.py
terminal_utils/choices_via_terminal.py
terminal_utils/lib/__init__.py
terminal_utils/lib/choices.py
terminal_utils/lib/terminal_tools.py
ers_terminal_utils-0.0.2.dist-info/LICENSE
ers_terminal_utils-0.0.2.dist-info/METADATA
ers_terminal_utils-0.0.2.dist-info/WHEEL
ers_terminal_utils-0.0.2.dist-info/top_level.txt
ers_terminal_utils-0.0.2.dist-info/RECORD
