Metadata-Version: 2.1
Name: ers-terminal-utils
Version: 0.0.2
Summary: A python package for UNIX terminal utilities
Author-email: Eliaquim Souza <eliaquim.rsv@gmail.com>
Maintainer-email: Eliaquim Souza <eliaquim.rsv@gmail.com>
License: MIT License
Project-URL: Homepage, https://github.com/eliaquimrs/terminal-utils
Project-URL: Documentation, https://github.com/eliaquimrs/terminal-utils?tab=readme-ov-file#readme
Project-URL: Repository, https://github.com/eliaquimrs/terminal-utils.git
Project-URL: Bug Tracker, https://github.com/eliaquimrs/terminal-utils/issues
Keywords: terminal,shell,python,bash,choices,terminal choices
Classifier: Development Status :: 4 - Beta
Classifier: Natural Language :: English
Classifier: Programming Language :: Python
Classifier: Operating System :: Unix
Classifier: Topic :: Utilities
Requires-Python: >=2.7
License-File: LICENSE
